req2/__init__.py
req2/adapters.py
req2/exceptions.py
req2/models.py
req2/sessions.py
req2/utils.py
req2-0.1.0.dist-info/licenses/LICENSE
req2-0.1.0.dist-info/METADATA
req2-0.1.0.dist-info/WHEEL
req2-0.1.0.dist-info/top_level.txt
req2-0.1.0.dist-info/RECORD
