Metadata-Version: 2.4
Name: req2
Version: 0.1.0
Summary: Requests-compatible HTTP client powered by pycurl with timing metrics
Author: AutoGenerated
License: Apache-2.0
Requires-Python: >=3.8
License-File: LICENSE
Requires-Dist: pycurl>=7.45.3
Provides-Extra: dev
Requires-Dist: pytest>=7.0; extra == "dev"
Provides-Extra: docs
Requires-Dist: sphinx>=7.0; extra == "docs"
Dynamic: license-file
